image_cropper-0.1.0.dist-info/METADATA
image_cropper-0.1.0.dist-info/WHEEL
image_cropper-0.1.0.dist-info/entry_points.txt
image_cropper-0.1.0.dist-info/licenses/LICENSE.md
image_cropper.libs/libgcc_s-e52197c3.so.1
image_cropper/__init__.py
image_cropper/image_cropper.cpython-39-aarch64-linux-gnu.so
image_cropper/image_cropper.pyi
image_cropper/main.py
image_cropper-0.1.0.dist-info/RECORD
