Metadata-Version: 2.4
Name: image-cropper
Version: 0.1.0
Classifier: Programming Language :: Rust
Classifier: Programming Language :: Python :: Implementation :: CPython
Classifier: Programming Language :: Python :: Implementation :: PyPy
Requires-Dist: typer[all]
License-File: LICENSE.md
Requires-Python: >=3.8
